{
  "team": {
    "name": "NIIGHTMARE",
    "fullName": "NIIGHTMARE ESPORTS",
    "region": {
      "en": "Lao PDR",
      "lo": "ສປປ ລາວ"
    }
  },
  "contact": {
    "email": "NiightmareEsports@outlook.com",
    "facebook": "https://facebook.com/niightmareesports",
    "instagram": "https://instagram.com/niightmareesports",
    "youtube": "https://youtube.com/@niightmareesports",
    "tiktok": "https://tiktok.com/@niightmareesports",
    "discord": ""
  },
  "contactPage": {
    "kicker": {
      "en": "Contact",
      "lo": "ຕິດຕໍ່"
    },
    "title": {
      "en": "Contact NIIGHTMARE",
      "lo": "ຕິດຕໍ່ NIIGHTMARE"
    },
    "intro": {
      "en": "Open the right conversation for sponsorship, media, recruitment, or community collaborations.",
      "lo": "ເລີ່ມຕົ້ນການຕິດຕໍ່ທີ່ຖືກທາງ ສໍາລັບສະປອນເຊີ, ສື່, ການຮັບສະໝັກ ຫຼື ການຮ່ວມມືກັບຊຸມຊົນ."
    },
    "deskLabel": {
      "en": "Team Contact",
      "lo": "ຊ່ອງທາງຕິດຕໍ່ທີມ"
    },
    "deskIntro": {
      "en": "Send sponsorship, media, event, scrim, recruitment, or official team enquiries.",
      "lo": "ສົ່ງຂໍ້ຄວາມເລື່ອງ sponsor, media, event, scrim, recruitment ຫຼື ການຕິດຕໍ່ທີມແບບທາງການ."
    },
    "infoLabel": {
      "en": "Direct Channels",
      "lo": "ຊ່ອງທາງໂດຍກົງ"
    },
    "mediaKitLabel": {
      "en": "Attachments",
      "lo": "ໄຟລ໌ແນບ"
    },
    "mediaKitDesc": {
      "en": "Attach documents, images, videos, proposals, or any files NIIGHTMARE should review.",
      "lo": "ແນບເອກະສານ, ຮູບ, ວິດີໂອ, proposal ຫຼື ໄຟລ໌ໃດໆ ທີ່ຕ້ອງການໃຫ້ NIIGHTMARE ກວດເບິ່ງ."
    },
    "mediaKitButton": {
      "en": "Attach / Send Files",
      "lo": "ແນບ / ສົ່ງໄຟລ໌"
    },
    "formLabel": {
      "en": "Start the Conversation",
      "lo": "ເລີ່ມການຕິດຕໍ່"
    },
    "formIntro": {
      "en": "Send the team your brief. We will route it to the right person.",
      "lo": "ສົ່ງ brief ຂອງທ່ານໃຫ້ທີມ ແລ້ວພວກເຮົາຈະສົ່ງຕໍ່ໃຫ້ຜູ້ຮັບຜິດຊອບ."
    },
    "fieldLabels": {
      "name": {
        "en": "Name",
        "lo": "ຊື່"
      },
      "email": {
        "en": "Email",
        "lo": "ອີເມວ"
      },
      "company": {
        "en": "Company / Organization",
        "lo": "ບໍລິສັດ / ອົງກອນ"
      },
      "type": {
        "en": "Enquiry Type",
        "lo": "ປະເພດການຕິດຕໍ່"
      },
      "message": {
        "en": "Message",
        "lo": "ຂໍ້ຄວາມ"
      },
      "attachments": {
        "en": "Attachments",
        "lo": "ໄຟລ໌ແນບ"
      }
    },
    "typeLabels": {
      "sponsorship": {
        "en": "Sponsorship",
        "lo": "ສະປອນເຊີ"
      },
      "media": {
        "en": "Media",
        "lo": "ສື່"
      },
      "general": {
        "en": "General",
        "lo": "ທົ່ວໄປ"
      },
      "tryout": {
        "en": "Tryout",
        "lo": "ທົດສອບທີມ"
      }
    },
    "channelLabels": {
      "email": {
        "en": "Business Email",
        "lo": "ອີເມວທຸລະກິດ"
      },
      "facebook": {
        "en": "Facebook",
        "lo": "Facebook"
      },
      "instagram": {
        "en": "Instagram",
        "lo": "Instagram"
      },
      "youtube": {
        "en": "YouTube",
        "lo": "YouTube"
      },
      "tiktok": {
        "en": "TikTok",
        "lo": "TikTok"
      },
      "discord": {
        "en": "Discord",
        "lo": "Discord"
      },
      "liquipedia": {
        "en": "Liquipedia",
        "lo": "Liquipedia"
      }
    },
    "submit": {
      "en": "Send Message",
      "lo": "ສົ່ງຂໍ້ຄວາມ"
    },
    "submitting": {
      "en": "Sending...",
      "lo": "ກໍາລັງສົ່ງ..."
    },
    "success": {
      "en": "Message sent. We will get back to you soon.",
      "lo": "ສົ່ງຂໍ້ຄວາມແລ້ວ. ພວກເຮົາຈະຕອບກັບໄວໆນີ້."
    },
    "error": {
      "en": "Something went wrong. Please email us directly at",
      "lo": "ມີບາງຢ່າງຜິດພາດ. ກະລຸນາສົ່ງອີເມວໂດຍກົງຫາ"
    }
  },
  "communityUrl": "",
  "formspreeEndpoint": "https://formspree.io/f/your-form-id",
  "mediaKitUrl": "/media-kit.pdf",
  "matchSchedule": {
    "enabled": false,
    "buttonLabel": {
      "en": "View Schedule",
      "lo": "ເບິ່ງຕາຕະລາງແຂ່ງ"
    },
    "title": {
      "en": "NIIGHTMARE Match Schedule",
      "lo": "ຕາຕະລາງແຂ່ງ NIIGHTMARE"
    },
    "intro": {
      "en": "Upcoming NIIGHTMARE fixtures curated by the team.",
      "lo": "ລາຍການແຂ່ງຂອງ NIIGHTMARE ຈາກຕາຕະລາງທີ່ອັບໂຫຼດ."
    },
    "emptyText": {
      "en": "No NIIGHTMARE schedule rows have been added yet.",
      "lo": "ຍັງບໍ່ມີລາຍການແຂ່ງຂອງ NIIGHTMARE."
    },
    "entries": []
  },
  "upcomingMatch": {
    "status": "next",
    "date": "2026-07-01T19:00:00+07:00",
    "game": "mlbb",
    "tournament": {
      "en": "WILD CARD 2026",
      "lo": "WILD CARD 2026"
    },
    "round": {
      "en": "Semi Final",
      "lo": "ຮອບຮອງຊະນະເລີດ"
    },
    "opponent": "ONIC",
    "opponentLogo": ""
  },
  "videos": [],
  "games": [
    {
      "id": "mlbb",
      "name": { "en": "Mobile Legends: Bang Bang", "lo": "Mobile Legends: Bang Bang" },
      "shortName": "MLBB",
      "enabled": true
    },
    {
      "id": "efootball",
      "name": { "en": "eFootball", "lo": "eFootball" },
      "shortName": "eFootball",
      "enabled": true
    }
  ],
  "gallery": {
    "page": {
      "kicker": { "en": "NIIGHTMARE ARCHIVE", "lo": "ຄັງພາບ NIIGHTMARE" },
      "title": { "en": "GALLERY", "lo": "ຄັງຮູບພາບ" },
      "intro": {
        "en": "Moments from competition, the team, and the community.",
        "lo": "ຮວບຮວມຊ່ວງເວລາຈາກການແຂ່ງຂັນ, ທີມ ແລະ ຊຸມຊົນ."
      }
    },
    "categories": [
      { "id": "team", "name": { "en": "Team", "lo": "ທີມ" } },
      { "id": "tournaments", "name": { "en": "Tournaments", "lo": "ການແຂ່ງຂັນ" } },
      { "id": "community", "name": { "en": "Community", "lo": "ຊຸມຊົນ" } }
    ],
    "items": []
  }
}
